bytecode_tools/__init__.py
bytecode_tools/byteplay.py
bytecode_tools/compatibility.py
bytecode_tools/constants.py
bytecode_tools/dis.py
bytecode_tools/opcodes.py
bytecode_tools/pyc_decoder.py
bytecode_tools/pycdecode.py
bytecode_tools/pydis.py
bytecode_tools/unmarshal.py
bytecode_tools/utils.py
bytecode_tools/common/__init__.py
bytecode_tools/common/compatibility.py
bytecode_tools/common/constants.py
bytecode_tools/common/decode_code_object.py
bytecode_tools/common/opcodes.py
bytecode_tools/utils/__init__.py
bytecode_tools-0.0.2.dist-info/LICENSE
bytecode_tools-0.0.2.dist-info/METADATA
bytecode_tools-0.0.2.dist-info/WHEEL
bytecode_tools-0.0.2.dist-info/top_level.txt
bytecode_tools-0.0.2.dist-info/RECORD
